jupyter_clipmagic/__init__.py
jupyter_clipmagic/clipmagic.py
jupyter_clipmagic-0.1.0.dist-info/METADATA
jupyter_clipmagic-0.1.0.dist-info/WHEEL
jupyter_clipmagic-0.1.0.dist-info/RECORD
