Metadata-Version: 2.4
Name: jupyter_clipmagic
Version: 0.1.0
Summary: IPython/Jupyter magic commands for copying code to clipboard
Author-email: Brett Naul <brettnaul@gmail.com>
License: MIT
Requires-Python: >=3.7
Requires-Dist: ipython
Requires-Dist: pyperclip
Provides-Extra: dev
Requires-Dist: pytest; extra == 'dev'
